ghalton/__init__.py
ghalton/_ghalton_wrapper.cpython-37m-darwin.so
ghalton/constants.py
ghalton/ghalton_wrapper.py
ghalton-0.6.2.dist-info/LICENSE.txt
ghalton-0.6.2.dist-info/METADATA
ghalton-0.6.2.dist-info/WHEEL
ghalton-0.6.2.dist-info/top_level.txt
ghalton-0.6.2.dist-info/RECORD
